mongo_cached_requests/__init__.py
mongo_cached_requests/client.py
mongo_cached_requests-0.1.6.dist-info/WHEEL
mongo_cached_requests-0.1.6.dist-info/METADATA
mongo_cached_requests-0.1.6.dist-info/RECORD
